feuersoftware/__init__.py
feuersoftware/api.py
feuersoftware/models.py
feuersoftware-0.2.4.dist-info/METADATA
feuersoftware-0.2.4.dist-info/WHEEL
feuersoftware-0.2.4.dist-info/top_level.txt
feuersoftware-0.2.4.dist-info/RECORD
