Metadata-Version: 2.4
Name: feuersoftware
Version: 0.2.4
Summary: Ein Python Modul um die Öffentliche Feuersoftware API.
Author-email: bouni <bouni-github@owee.de>
Project-URL: Homepage, https://github.com/Bouni/feuersoftware
Project-URL: Repository, https://github.com/Bouni/feuersoftware.git
Project-URL: Issues, https://github.com/Bouni/feuersoftware/issues
Requires-Python: >=3.12
Requires-Dist: pydantic>=2.9.2
Requires-Dist: requests>=2.32.3
